crossify/__init__.py
crossify/__main__.py
crossify/crossings.py
crossify/intersections.py
crossify/io.py
crossify/opensidewalks.py
crossify/validators.py
crossify-0.1.4.dist-info/DESCRIPTION.rst
crossify-0.1.4.dist-info/METADATA
crossify-0.1.4.dist-info/RECORD
crossify-0.1.4.dist-info/WHEEL
crossify-0.1.4.dist-info/entry_points.txt
crossify-0.1.4.dist-info/metadata.json
crossify-0.1.4.dist-info/top_level.txt
